beaver/__init__.py
beaver/beaver.py
beavr-1.0.3.dist-info/LICENSE
beavr-1.0.3.dist-info/METADATA
beavr-1.0.3.dist-info/WHEEL
beavr-1.0.3.dist-info/entry_points.txt
beavr-1.0.3.dist-info/top_level.txt
beavr-1.0.3.dist-info/RECORD
