Metadata-Version: 2.1
Name: beavr
Version: 1.0.3
Summary: An animal that eats logs
Home-page: https://github.com/wcarhart/beaver
Author: Will Carhart
Author-email: wcarhart@sandiego.edu
License: MIT
Platform: UNKNOWN
Classifier: License :: OSI Approved :: MIT License
Classifier: Programming Language :: Python :: 3
Classifier: Programming Language :: Python :: 3.7
